logger.py
a_logger-0.1.dist-info/METADATA
a_logger-0.1.dist-info/WHEEL
a_logger-0.1.dist-info/top_level.txt
a_logger-0.1.dist-info/RECORD
